{
  "metadata": {
    "source_fichier": "source_data/offres_emploi_it_maroc.json",
    "date_ingestion": "2026-05-09T20:30:44.057655",
    "partition": "menajobs/2023_08",
    "nb_offres": 88
  },
  "offres": [
    {
      "id_offre": "MEX-10006",
      "source": "MenaJobs",
      "titre_poste": "Architecte IT 1 à 3 ans",
      "entreprise": "TechCorp 11",
      "ville": "Tanger",
      "date_publication": "2023-08-20",
      "type_contrat": "CDD",
      "salaire_brut": "25K - 35K MAD",
      "experience_requise": "1 à 3 ans",
      "teletravail": "Hybride",
      "description": "Nous recherchons un Architecte IT pour rejoindre notre équipe. Maîtrise requise : Power BI, Airflow, Kafka, Java, SQL.",
      "competences_brut": "Power BI, Airflow, Kafka, Java, SQL"
    },
    {
      "id_offre": "MEX-10044",
      "source": "MenaJobs",
      "titre_poste": "Data Analyst Débutant",
      "entreprise": "TechCorp 42",
      "ville": "Tanger",
      "date_publication": "2023-08-07",
      "type_contrat": "CDI",
      "salaire_brut": "8K - 12K MAD",
      "experience_requise": "Débutant",
      "teletravail": "Sur site",
      "description": "Nous recherchons un Data Analyst pour rejoindre notre équipe. Maîtrise requise : Airflow, Kafka, JavaScript, SQL.",
      "competences_brut": "Airflow, Kafka, JavaScript, SQL"
    },
    {
      "id_offre": "MEX-10113",
      "source": "MenaJobs",
      "titre_poste": "Data Scientist Senior (5+ ans)",
      "entreprise": "TechCorp 39",
      "ville": "Tanger",
      "date_publication": "2023-08-26",
      "type_contrat": "CDD",
      "salaire_brut": "28000 à 43000 DH",
      "experience_requise": "Senior (5+ ans)",
      "teletravail": "Télétravail total",
      "description": "Nous recherchons un Data Scientist pour rejoindre notre équipe. Maîtrise requise : React, Java, Airflow, SQL, JavaScript.",
      "competences_brut": "React, Java, Airflow, SQL, JavaScript"
    },
    {
      "id_offre": "MEX-10130",
      "source": "MenaJobs",
      "titre_poste": "Architecte IT Senior (5+ ans)",
      "entreprise": "TechCorp 7",
      "ville": "Fès",
      "date_publication": "2023-08-05",
      "type_contrat": "Freelance",
      "salaire_brut": "45000 à 63000 DH",
      "experience_requise": "Senior (5+ ans)",
      "teletravail": "Hybride",
      "description": "Nous recherchons un Architecte IT pour rejoindre notre équipe. Maîtrise requise : PostgreSQL, Power BI, Spring.",
      "competences_brut": "PostgreSQL, Power BI, Spring"
    },
    {
      "id_offre": "MEX-10268",
      "source": "MenaJobs",
      "titre_poste": "Data Analyst 3 à 5 ans",
      "entreprise": "TechCorp 13",
      "ville": "Casablanca",
      "date_publication": "2023-08-29",
      "type_contrat": "CDI",
      "salaire_brut": "14K - 22K MAD",
      "experience_requise": "3 à 5 ans",
      "teletravail": "Hybride",
      "description": "Nous recherchons un Data Analyst pour rejoindre notre équipe. Maîtrise requise : React, Java, JavaScript, Docker.",
      "competences_brut": "React, Java, JavaScript, Docker"
    },
    {
      "id_offre": "MEX-10271",
      "source": "MenaJobs",
      "titre_poste": "DevOps 3 à 5 ans",
      "entreprise": "TechCorp 34",
      "ville": "Rabat",
      "date_publication": "2023-08-16",
      "type_contrat": "Freelance",
      "salaire_brut": "19K - 28K MAD",
      "experience_requise": "3 à 5 ans",
      "teletravail": "Télétravail total",
      "description": "Nous recherchons un DevOps pour rejoindre notre équipe. Maîtrise requise : Airflow, SQL, Java.",
      "competences_brut": "Airflow, SQL, Java"
    },
    {
      "id_offre": "MEX-10360",
      "source": "MenaJobs",
      "titre_poste": "Data Scientist 3 à 5 ans",
      "entreprise": "TechCorp 38",
      "ville": "Casablanca",
      "date_publication": "2023-08-17",
      "type_contrat": "CDI",
      "salaire_brut": "Selon profil",
      "experience_requise": "3 à 5 ans",
      "teletravail": "Sur site",
      "description": "Nous recherchons un Data Scientist pour rejoindre notre équipe. Maîtrise requise : SQL, Python, Spring, Java, AWS.",
      "competences_brut": "SQL, Python, Spring, Java, AWS"
    },
    {
      "id_offre": "MEX-10424",
      "source": "MenaJobs",
      "titre_poste": "DevOps Senior (5+ ans)",
      "entreprise": "TechCorp 41",
      "ville": "Casablanca",
      "date_publication": "2023-08-22",
      "type_contrat": "Freelance",
      "salaire_brut": "25000 à 36000 DH",
      "experience_requise": "Senior (5+ ans)",
      "teletravail": "Télétravail total",
      "description": "Nous recherchons un DevOps pour rejoindre notre équipe. Maîtrise requise : Kafka, Power BI.",
      "competences_brut": "Kafka, Power BI"
    },
    {
      "id_offre": "MEX-10546",
      "source": "MenaJobs",
      "titre_poste": "Admin Systèmes & Réseaux Senior (5+ ans)",
      "entreprise": "TechCorp 19",
      "ville": "Fès",
      "date_publication": "2023-08-11",
      "type_contrat": "Freelance",
      "salaire_brut": "14K - 21K MAD",
      "experience_requise": "Senior (5+ ans)",
      "teletravail": "Télétravail total",
      "description": "Nous recherchons un Admin Systèmes & Réseaux pour rejoindre notre équipe. Maîtrise requise : Docker, Spark, AWS.",
      "competences_brut": "Docker, Spark, AWS"
    },
    {
      "id_offre": "MEX-10594",
      "source": "MenaJobs",
      "titre_poste": "Support IT Senior (5+ ans)",
      "entreprise": "TechCorp 11",
      "ville": "Tanger",
      "date_publication": "2023-08-09",
      "type_contrat": "CDI",
      "salaire_brut": "9K - 14K MAD",
      "experience_requise": "Senior (5+ ans)",
      "teletravail": "Sur site",
      "description": "Nous recherchons un Support IT pour rejoindre notre équipe. Maîtrise requise : PostgreSQL, Python, Power BI, Kafka, Airflow.",
      "competences_brut": "PostgreSQL, Python, Power BI, Kafka, Airflow"
    },
    {
      "id_offre": "MEX-10600",
      "source": "MenaJobs",
      "titre_poste": "Architecte IT 1 à 3 ans",
      "entreprise": "TechCorp 46",
      "ville": "Casablanca",
      "date_publication": "2023-08-04",
      "type_contrat": "CDI",
      "salaire_brut": "25K - 35K MAD",
      "experience_requise": "1 à 3 ans",
      "teletravail": "Télétravail total",
      "description": "Nous recherchons un Architecte IT pour rejoindre notre équipe. Maîtrise requise : Kafka, Spring, Airflow.",
      "competences_brut": "Kafka, Spring, Airflow"
    },
    {
      "id_offre": "MEX-10623",
      "source": "MenaJobs",
      "titre_poste": "Data Analyst Senior (5+ ans)",
      "entreprise": "TechCorp 16",
      "ville": "Tanger",
      "date_publication": "2023-08-20",
      "type_contrat": "CDI",
      "salaire_brut": "18000 à 28000 DH",
      "experience_requise": "Senior (5+ ans)",
      "teletravail": "Télétravail total",
      "description": "Nous recherchons un Data Analyst pour rejoindre notre équipe. Maîtrise requise : Java, PostgreSQL.",
      "competences_brut": "Java, PostgreSQL"
    },
    {
      "id_offre": "MEX-10691",
      "source": "MenaJobs",
      "titre_poste": "Data Scientist Senior (5+ ans)",
      "entreprise": "TechCorp 29",
      "ville": "Casablanca",
      "date_publication": "2023-08-31",
      "type_contrat": "CDI",
      "salaire_brut": "28000 à 43000 DH",
      "experience_requise": "Senior (5+ ans)",
      "teletravail": "Télétravail total",
      "description": "Nous recherchons un Data Scientist pour rejoindre notre équipe. Maîtrise requise : React, SQL, PostgreSQL.",
      "competences_brut": "React, SQL, PostgreSQL"
    },
    {
      "id_offre": "MEX-10782",
      "source": "MenaJobs",
      "titre_poste": "Admin Systèmes & Réseaux 1 à 3 ans",
      "entreprise": "TechCorp 10",
      "ville": "Casablanca",
      "date_publication": "2023-08-30",
      "type_contrat": "CDI",
      "salaire_brut": "8000 à 12000 DH",
      "experience_requise": "1 à 3 ans",
      "teletravail": "Télétravail total",
      "description": "Nous recherchons un Admin Systèmes & Réseaux pour rejoindre notre équipe. Maîtrise requise : Docker, Python, Kafka, Airflow, SQL.",
      "competences_brut": "Docker, Python, Kafka, Airflow, SQL"
    },
    {
      "id_offre": "MEX-10918",
      "source": "MenaJobs",
      "titre_poste": "Développeur Full Stack Senior (5+ ans)",
      "entreprise": "TechCorp 16",
      "ville": "Casablanca",
      "date_publication": "2023-08-24",
      "type_contrat": "Freelance",
      "salaire_brut": "21000 à 32000 DH",
      "experience_requise": "Senior (5+ ans)",
      "teletravail": "Télétravail total",
      "description": "Nous recherchons un Développeur Full Stack pour rejoindre notre équipe. Maîtrise requise : Power BI, Docker, Spring.",
      "competences_brut": "Power BI, Docker, Spring"
    },
    {
      "id_offre": "MEX-10941",
      "source": "MenaJobs",
      "titre_poste": "Data Scientist 1 à 3 ans",
      "entreprise": "TechCorp 1",
      "ville": "Marrakech",
      "date_publication": "2023-08-06",
      "type_contrat": "CDI",
      "salaire_brut": "16000 à 24000 DH",
      "experience_requise": "1 à 3 ans",
      "teletravail": "Sur site",
      "description": "Nous recherchons un Data Scientist pour rejoindre notre équipe. Maîtrise requise : Spring, PostgreSQL.",
      "competences_brut": "Spring, PostgreSQL"
    },
    {
      "id_offre": "MEX-11032",
      "source": "MenaJobs",
      "titre_poste": "Admin Systèmes & Réseaux 3 à 5 ans",
      "entreprise": "TechCorp 33",
      "ville": "Tanger",
      "date_publication": "2023-08-29",
      "type_contrat": "CDI",
      "salaire_brut": "11000 à 16000 DH",
      "experience_requise": "3 à 5 ans",
      "teletravail": "Sur site",
      "description": "Nous recherchons un Admin Systèmes & Réseaux pour rejoindre notre équipe. Maîtrise requise : Airflow, JavaScript, Docker.",
      "competences_brut": "Airflow, JavaScript, Docker"
    },
    {
      "id_offre": "MEX-11241",
      "source": "MenaJobs",
      "titre_poste": "Data Engineer 3 à 5 ans",
      "entreprise": "TechCorp 24",
      "ville": "Casablanca",
      "date_publication": "2023-08-22",
      "type_contrat": "CDD",
      "salaire_brut": "21K - 30K MAD",
      "experience_requise": "3 à 5 ans",
      "teletravail": "Hybride",
      "description": "Nous recherchons un Data Engineer pour rejoindre notre équipe. Maîtrise requise : AWS, PostgreSQL, Spring, JavaScript, Airflow.",
      "competences_brut": "AWS, PostgreSQL, Spring, JavaScript, Airflow"
    },
    {
      "id_offre": "MEX-11307",
      "source": "MenaJobs",
      "titre_poste": "Développeur Full Stack Senior (5+ ans)",
      "entreprise": "TechCorp 11",
      "ville": "Tanger",
      "date_publication": "2023-08-21",
      "type_contrat": "CDI",
      "salaire_brut": "21000 à 32000 DH",
      "experience_requise": "Senior (5+ ans)",
      "teletravail": "Hybride",
      "description": "Nous recherchons un Développeur Full Stack pour rejoindre notre équipe. Maîtrise requise : Java, Spark.",
      "competences_brut": "Java, Spark"
    },
    {
      "id_offre": "MEX-11411",
      "source": "MenaJobs",
      "titre_poste": "Développeur Full Stack Senior (5+ ans)",
      "entreprise": "TechCorp 13",
      "ville": "Tanger",
      "date_publication": "2023-08-25",
      "type_contrat": "CDI",
      "salaire_brut": "21000 à 32000 DH",
      "experience_requise": "Senior (5+ ans)",
      "teletravail": "Hybride",
      "description": "Nous recherchons un Développeur Full Stack pour rejoindre notre équipe. Maîtrise requise : JavaScript, SQL.",
      "competences_brut": "JavaScript, SQL"
    },
    {
      "id_offre": "MEX-11424",
      "source": "MenaJobs",
      "titre_poste": "Architecte IT Senior (5+ ans)",
      "entreprise": "TechCorp 20",
      "ville": "Casablanca",
      "date_publication": "2023-08-16",
      "type_contrat": "CDI",
      "salaire_brut": "45000 à 63000 DH",
      "experience_requise": "Senior (5+ ans)",
      "teletravail": "Sur site",
      "description": "Nous recherchons un Architecte IT pour rejoindre notre équipe. Maîtrise requise : Python, Docker, Java, JavaScript.",
      "competences_brut": "Python, Docker, Java, JavaScript"
    },
    {
      "id_offre": "MEX-11494",
      "source": "MenaJobs",
      "titre_poste": "Admin Systèmes & Réseaux Senior (5+ ans)",
      "entreprise": "TechCorp 1",
      "ville": "Casablanca",
      "date_publication": "2023-08-30",
      "type_contrat": "CDI",
      "salaire_brut": "14000 à 21000 DH",
      "experience_requise": "Senior (5+ ans)",
      "teletravail": "Hybride",
      "description": "Nous recherchons un Admin Systèmes & Réseaux pour rejoindre notre équipe. Maîtrise requise : PostgreSQL, Java, Docker.",
      "competences_brut": "PostgreSQL, Java, Docker"
    },
    {
      "id_offre": "MEX-11588",
      "source": "MenaJobs",
      "titre_poste": "Data Analyst 3 à 5 ans",
      "entreprise": "TechCorp 22",
      "ville": "Rabat",
      "date_publication": "2023-08-10",
      "type_contrat": "CDI",
      "salaire_brut": "Confidentiel",
      "experience_requise": "3 à 5 ans",
      "teletravail": "Hybride",
      "description": "Nous recherchons un Data Analyst pour rejoindre notre équipe. Maîtrise requise : PostgreSQL, Python, AWS, JavaScript.",
      "competences_brut": "PostgreSQL, Python, AWS, JavaScript"
    },
    {
      "id_offre": "MEX-11655",
      "source": "MenaJobs",
      "titre_poste": "DevOps 3 à 5 ans",
      "entreprise": "TechCorp 42",
      "ville": "Tanger",
      "date_publication": "2023-08-15",
      "type_contrat": "CDI",
      "salaire_brut": "19K - 28K MAD",
      "experience_requise": "3 à 5 ans",
      "teletravail": "Sur site",
      "description": "Nous recherchons un DevOps pour rejoindre notre équipe. Maîtrise requise : SQL, Power BI, Docker.",
      "competences_brut": "SQL, Power BI, Docker"
    },
    {
      "id_offre": "MEX-11673",
      "source": "MenaJobs",
      "titre_poste": "Support IT 1 à 3 ans",
      "entreprise": "TechCorp 8",
      "ville": "Casablanca",
      "date_publication": "2023-08-20",
      "type_contrat": "CDI",
      "salaire_brut": "5000 à 8000 DH",
      "experience_requise": "1 à 3 ans",
      "teletravail": "Sur site",
      "description": "Nous recherchons un Support IT pour rejoindre notre équipe. Maîtrise requise : SQL, Spring, Airflow, Java, React.",
      "competences_brut": "SQL, Spring, Airflow, Java, React"
    },
    {
      "id_offre": "MEX-11674",
      "source": "MenaJobs",
      "titre_poste": "Data Engineer Débutant",
      "entreprise": "TechCorp 48",
      "ville": "Tanger",
      "date_publication": "2023-08-05",
      "type_contrat": "CDI",
      "salaire_brut": "Confidentiel",
      "experience_requise": "Débutant",
      "teletravail": "Sur site",
      "description": "Nous recherchons un Data Engineer pour rejoindre notre équipe. Maîtrise requise : Java, AWS, PostgreSQL, Airflow.",
      "competences_brut": "Java, AWS, PostgreSQL, Airflow"
    },
    {
      "id_offre": "MEX-11737",
      "source": "MenaJobs",
      "titre_poste": "Support IT 3 à 5 ans",
      "entreprise": "TechCorp 33",
      "ville": "Fès",
      "date_publication": "2023-08-09",
      "type_contrat": "CDI",
      "salaire_brut": "7000 à 11000 DH",
      "experience_requise": "3 à 5 ans",
      "teletravail": "Sur site",
      "description": "Nous recherchons un Support IT pour rejoindre notre équipe. Maîtrise requise : JavaScript, Kafka, SQL, Python, PostgreSQL.",
      "competences_brut": "JavaScript, Kafka, SQL, Python, PostgreSQL"
    },
    {
      "id_offre": "MEX-11759",
      "source": "MenaJobs",
      "titre_poste": "Support IT 1 à 3 ans",
      "entreprise": "TechCorp 8",
      "ville": "Rabat",
      "date_publication": "2023-08-17",
      "type_contrat": "Freelance",
      "salaire_brut": "5K - 8K MAD",
      "experience_requise": "1 à 3 ans",
      "teletravail": "Sur site",
      "description": "Nous recherchons un Support IT pour rejoindre notre équipe. Maîtrise requise : SQL, Power BI, Python.",
      "competences_brut": "SQL, Power BI, Python"
    },
    {
      "id_offre": "MEX-11824",
      "source": "MenaJobs",
      "titre_poste": "Data Engineer Senior (5+ ans)",
      "entreprise": "TechCorp 47",
      "ville": "Casablanca",
      "date_publication": "2023-08-15",
      "type_contrat": "CDI",
      "salaire_brut": "27000 à 39000 DH",
      "experience_requise": "Senior (5+ ans)",
      "teletravail": "Sur site",
      "description": "Nous recherchons un Data Engineer pour rejoindre notre équipe. Maîtrise requise : Kafka, Power BI.",
      "competences_brut": "Kafka, Power BI"
    },
    {
      "id_offre": "MEX-11851",
      "source": "MenaJobs",
      "titre_poste": "Data Analyst 3 à 5 ans",
      "entreprise": "TechCorp 30",
      "ville": "Casablanca",
      "date_publication": "2023-08-02",
      "type_contrat": "CDI",
      "salaire_brut": "Confidentiel",
      "experience_requise": "3 à 5 ans",
      "teletravail": "Hybride",
      "description": "Nous recherchons un Data Analyst pour rejoindre notre équipe. Maîtrise requise : Power BI, AWS.",
      "competences_brut": "Power BI, AWS"
    },
    {
      "id_offre": "MEX-11864",
      "source": "MenaJobs",
      "titre_poste": "Développeur Frontend Débutant",
      "entreprise": "TechCorp 20",
      "ville": "Casablanca",
      "date_publication": "2023-08-07",
      "type_contrat": "CDI",
      "salaire_brut": "8000 à 12000 DH",
      "experience_requise": "Débutant",
      "teletravail": "Télétravail total",
      "description": "Nous recherchons un Développeur Frontend pour rejoindre notre équipe. Maîtrise requise : Spark, JavaScript, Java, React, Python.",
      "competences_brut": "Spark, JavaScript, Java, React, Python"
    },
    {
      "id_offre": "MEX-11894",
      "source": "MenaJobs",
      "titre_poste": "Data Engineer 1 à 3 ans",
      "entreprise": "TechCorp 20",
      "ville": "Casablanca",
      "date_publication": "2023-08-31",
      "type_contrat": "CDI",
      "salaire_brut": "15K - 22K MAD",
      "experience_requise": "1 à 3 ans",
      "teletravail": "Télétravail total",
      "description": "Nous recherchons un Data Engineer pour rejoindre notre équipe. Maîtrise requise : Spark, SQL, Docker, Spring.",
      "competences_brut": "Spark, SQL, Docker, Spring"
    },
    {
      "id_offre": "MEX-11911",
      "source": "MenaJobs",
      "titre_poste": "Développeur Full Stack Senior (5+ ans)",
      "entreprise": "TechCorp 43",
      "ville": "Rabat",
      "date_publication": "2023-08-16",
      "type_contrat": "Freelance",
      "salaire_brut": "Selon profil",
      "experience_requise": "Senior (5+ ans)",
      "teletravail": "Télétravail total",
      "description": "Nous recherchons un Développeur Full Stack pour rejoindre notre équipe. Maîtrise requise : Power BI, Kafka.",
      "competences_brut": "Power BI, Kafka"
    },
    {
      "id_offre": "MEX-12062",
      "source": "MenaJobs",
      "titre_poste": "Data Scientist 3 à 5 ans",
      "entreprise": "TechCorp 22",
      "ville": "Casablanca",
      "date_publication": "2023-08-30",
      "type_contrat": "CDI",
      "salaire_brut": "22000 à 33000 DH",
      "experience_requise": "3 à 5 ans",
      "teletravail": "Télétravail total",
      "description": "Nous recherchons un Data Scientist pour rejoindre notre équipe. Maîtrise requise : Power BI, Python, JavaScript.",
      "competences_brut": "Power BI, Python, JavaScript"
    },
    {
      "id_offre": "MEX-12066",
      "source": "MenaJobs",
      "titre_poste": "Support IT 1 à 3 ans",
      "entreprise": "TechCorp 6",
      "ville": "Casablanca",
      "date_publication": "2023-08-16",
      "type_contrat": "CDI",
      "salaire_brut": "5K - 8K MAD",
      "experience_requise": "1 à 3 ans",
      "teletravail": "Télétravail total",
      "description": "Nous recherchons un Support IT pour rejoindre notre équipe. Maîtrise requise : Spring, AWS, React, Airflow, Kafka.",
      "competences_brut": "Spring, AWS, React, Airflow, Kafka"
    },
    {
      "id_offre": "MEX-12084",
      "source": "MenaJobs",
      "titre_poste": "Développeur Full Stack Senior (5+ ans)",
      "entreprise": "TechCorp 13",
      "ville": "Casablanca",
      "date_publication": "2023-08-27",
      "type_contrat": "Freelance",
      "salaire_brut": "À débattre",
      "experience_requise": "Senior (5+ ans)",
      "teletravail": "Télétravail total",
      "description": "Nous recherchons un Développeur Full Stack pour rejoindre notre équipe. Maîtrise requise : Docker, Power BI.",
      "competences_brut": "Docker, Power BI"
    },
    {
      "id_offre": "MEX-12372",
      "source": "MenaJobs",
      "titre_poste": "Support IT 1 à 3 ans",
      "entreprise": "TechCorp 44",
      "ville": "Tanger",
      "date_publication": "2023-08-17",
      "type_contrat": "CDI",
      "salaire_brut": "5000 à 8000 DH",
      "experience_requise": "1 à 3 ans",
      "teletravail": "Télétravail total",
      "description": "Nous recherchons un Support IT pour rejoindre notre équipe. Maîtrise requise : PostgreSQL, JavaScript, React, Power BI, Spring.",
      "competences_brut": "PostgreSQL, JavaScript, React, Power BI, Spring"
    },
    {
      "id_offre": "MEX-12481",
      "source": "MenaJobs",
      "titre_poste": "Développeur Full Stack 1 à 3 ans",
      "entreprise": "TechCorp 44",
      "ville": "Rabat",
      "date_publication": "2023-08-27",
      "type_contrat": "CDI",
      "salaire_brut": "À débattre",
      "experience_requise": "1 à 3 ans",
      "teletravail": "Hybride",
      "description": "Nous recherchons un Développeur Full Stack pour rejoindre notre équipe. Maîtrise requise : PostgreSQL, Docker, SQL, Python.",
      "competences_brut": "PostgreSQL, Docker, SQL, Python"
    },
    {
      "id_offre": "MEX-12489",
      "source": "MenaJobs",
      "titre_poste": "Admin Systèmes & Réseaux 1 à 3 ans",
      "entreprise": "TechCorp 44",
      "ville": "Fès",
      "date_publication": "2023-08-22",
      "type_contrat": "Freelance",
      "salaire_brut": "8K - 12K MAD",
      "experience_requise": "1 à 3 ans",
      "teletravail": "Sur site",
      "description": "Nous recherchons un Admin Systèmes & Réseaux pour rejoindre notre équipe. Maîtrise requise : Python, Kafka, PostgreSQL, SQL, AWS.",
      "competences_brut": "Python, Kafka, PostgreSQL, SQL, AWS"
    },
    {
      "id_offre": "MEX-12507",
      "source": "MenaJobs",
      "titre_poste": "Data Engineer 3 à 5 ans",
      "entreprise": "TechCorp 34",
      "ville": "Rabat",
      "date_publication": "2023-08-07",
      "type_contrat": "CDI",
      "salaire_brut": "21K - 30K MAD",
      "experience_requise": "3 à 5 ans",
      "teletravail": "Télétravail total",
      "description": "Nous recherchons un Data Engineer pour rejoindre notre équipe. Maîtrise requise : PostgreSQL, React, Kafka.",
      "competences_brut": "PostgreSQL, React, Kafka"
    },
    {
      "id_offre": "MEX-12531",
      "source": "MenaJobs",
      "titre_poste": "Développeur Full Stack 1 à 3 ans",
      "entreprise": "TechCorp 1",
      "ville": "Casablanca",
      "date_publication": "2023-08-20",
      "type_contrat": "CDI",
      "salaire_brut": "12K - 18K MAD",
      "experience_requise": "1 à 3 ans",
      "teletravail": "Télétravail total",
      "description": "Nous recherchons un Développeur Full Stack pour rejoindre notre équipe. Maîtrise requise : Python, JavaScript, SQL, PostgreSQL.",
      "competences_brut": "Python, JavaScript, SQL, PostgreSQL"
    },
    {
      "id_offre": "MEX-12587",
      "source": "MenaJobs",
      "titre_poste": "Data Scientist 3 à 5 ans",
      "entreprise": "TechCorp 31",
      "ville": "Tanger",
      "date_publication": "2023-08-26",
      "type_contrat": "CDI",
      "salaire_brut": "22K - 33K MAD",
      "experience_requise": "3 à 5 ans",
      "teletravail": "Télétravail total",
      "description": "Nous recherchons un Data Scientist pour rejoindre notre équipe. Maîtrise requise : JavaScript, React, Spring.",
      "competences_brut": "JavaScript, React, Spring"
    },
    {
      "id_offre": "MEX-12602",
      "source": "MenaJobs",
      "titre_poste": "Admin Systèmes & Réseaux 1 à 3 ans",
      "entreprise": "TechCorp 13",
      "ville": "Tanger",
      "date_publication": "2023-08-27",
      "type_contrat": "Freelance",
      "salaire_brut": "8000 à 12000 DH",
      "experience_requise": "1 à 3 ans",
      "teletravail": "Sur site",
      "description": "Nous recherchons un Admin Systèmes & Réseaux pour rejoindre notre équipe. Maîtrise requise : Airflow, Spark.",
      "competences_brut": "Airflow, Spark"
    },
    {
      "id_offre": "MEX-12685",
      "source": "MenaJobs",
      "titre_poste": "DevOps 3 à 5 ans",
      "entreprise": "TechCorp 11",
      "ville": "Rabat",
      "date_publication": "2023-08-04",
      "type_contrat": "CDI",
      "salaire_brut": "À débattre",
      "experience_requise": "3 à 5 ans",
      "teletravail": "Hybride",
      "description": "Nous recherchons un DevOps pour rejoindre notre équipe. Maîtrise requise : Kafka, Java.",
      "competences_brut": "Kafka, Java"
    },
    {
      "id_offre": "MEX-12797",
      "source": "MenaJobs",
      "titre_poste": "Développeur Frontend 1 à 3 ans",
      "entreprise": "TechCorp 44",
      "ville": "Rabat",
      "date_publication": "2023-08-21",
      "type_contrat": "CDI",
      "salaire_brut": "10K - 15K MAD",
      "experience_requise": "1 à 3 ans",
      "teletravail": "Sur site",
      "description": "Nous recherchons un Développeur Frontend pour rejoindre notre équipe. Maîtrise requise : Java, React, PostgreSQL, Kafka.",
      "competences_brut": "Java, React, PostgreSQL, Kafka"
    },
    {
      "id_offre": "MEX-12932",
      "source": "MenaJobs",
      "titre_poste": "Admin Systèmes & Réseaux Débutant",
      "entreprise": "TechCorp 49",
      "ville": "Casablanca",
      "date_publication": "2023-08-12",
      "type_contrat": "Freelance",
      "salaire_brut": "6000 à 9000 DH",
      "experience_requise": "Débutant",
      "teletravail": "Hybride",
      "description": "Nous recherchons un Admin Systèmes & Réseaux pour rejoindre notre équipe. Maîtrise requise : Docker, AWS.",
      "competences_brut": "Docker, AWS"
    },
    {
      "id_offre": "MEX-12946",
      "source": "MenaJobs",
      "titre_poste": "DevOps 3 à 5 ans",
      "entreprise": "TechCorp 15",
      "ville": "Casablanca",
      "date_publication": "2023-08-18",
      "type_contrat": "CDI",
      "salaire_brut": "19000 à 28000 DH",
      "experience_requise": "3 à 5 ans",
      "teletravail": "Hybride",
      "description": "Nous recherchons un DevOps pour rejoindre notre équipe. Maîtrise requise : Power BI, PostgreSQL, Python, Docker.",
      "competences_brut": "Power BI, PostgreSQL, Python, Docker"
    },
    {
      "id_offre": "MEX-12976",
      "source": "MenaJobs",
      "titre_poste": "Architecte IT 1 à 3 ans",
      "entreprise": "TechCorp 26",
      "ville": "Fès",
      "date_publication": "2023-08-29",
      "type_contrat": "Freelance",
      "salaire_brut": "25K - 35K MAD",
      "experience_requise": "1 à 3 ans",
      "teletravail": "Hybride",
      "description": "Nous recherchons un Architecte IT pour rejoindre notre équipe. Maîtrise requise : Power BI, AWS, SQL.",
      "competences_brut": "Power BI, AWS, SQL"
    },
    {
      "id_offre": "MEX-13005",
      "source": "MenaJobs",
      "titre_poste": "Data Scientist Senior (5+ ans)",
      "entreprise": "TechCorp 8",
      "ville": "Casablanca",
      "date_publication": "2023-08-19",
      "type_contrat": "CDI",
      "salaire_brut": "28K - 43K MAD",
      "experience_requise": "Senior (5+ ans)",
      "teletravail": "Hybride",
      "description": "Nous recherchons un Data Scientist pour rejoindre notre équipe. Maîtrise requise : React, Java, PostgreSQL, Airflow.",
      "competences_brut": "React, Java, PostgreSQL, Airflow"
    },
    {
      "id_offre": "MEX-13083",
      "source": "MenaJobs",
      "titre_poste": "Développeur Frontend 3 à 5 ans",
      "entreprise": "TechCorp 47",
      "ville": "Rabat",
      "date_publication": "2023-08-07",
      "type_contrat": "CDD",
      "salaire_brut": "14000 à 21000 DH",
      "experience_requise": "3 à 5 ans",
      "teletravail": "Sur site",
      "description": "Nous recherchons un Développeur Frontend pour rejoindre notre équipe. Maîtrise requise : Airflow, SQL, JavaScript, AWS.",
      "competences_brut": "Airflow, SQL, JavaScript, AWS"
    },
    {
      "id_offre": "MEX-13120",
      "source": "MenaJobs",
      "titre_poste": "Admin Systèmes & Réseaux 1 à 3 ans",
      "entreprise": "TechCorp 34",
      "ville": "Casablanca",
      "date_publication": "2023-08-26",
      "type_contrat": "CDI",
      "salaire_brut": "8000 à 12000 DH",
      "experience_requise": "1 à 3 ans",
      "teletravail": "Hybride",
      "description": "Nous recherchons un Admin Systèmes & Réseaux pour rejoindre notre équipe. Maîtrise requise : React, Python.",
      "competences_brut": "React, Python"
    },
    {
      "id_offre": "MEX-13174",
      "source": "MenaJobs",
      "titre_poste": "Data Scientist Senior (5+ ans)",
      "entreprise": "TechCorp 30",
      "ville": "Rabat",
      "date_publication": "2023-08-14",
      "type_contrat": "CDD",
      "salaire_brut": "28000 à 43000 DH",
      "experience_requise": "Senior (5+ ans)",
      "teletravail": "Sur site",
      "description": "Nous recherchons un Data Scientist pour rejoindre notre équipe. Maîtrise requise : Power BI, React.",
      "competences_brut": "Power BI, React"
    },
    {
      "id_offre": "MEX-13209",
      "source": "MenaJobs",
      "titre_poste": "Architecte IT 3 à 5 ans",
      "entreprise": "TechCorp 1",
      "ville": "Casablanca",
      "date_publication": "2023-08-10",
      "type_contrat": "CDI",
      "salaire_brut": "35000 à 49000 DH",
      "experience_requise": "3 à 5 ans",
      "teletravail": "Sur site",
      "description": "Nous recherchons un Architecte IT pour rejoindre notre équipe. Maîtrise requise : JavaScript, Docker, PostgreSQL.",
      "competences_brut": "JavaScript, Docker, PostgreSQL"
    },
    {
      "id_offre": "MEX-13264",
      "source": "MenaJobs",
      "titre_poste": "Développeur Full Stack Senior (5+ ans)",
      "entreprise": "TechCorp 11",
      "ville": "Rabat",
      "date_publication": "2023-08-30",
      "type_contrat": "CDI",
      "salaire_brut": "21K - 32K MAD",
      "experience_requise": "Senior (5+ ans)",
      "teletravail": "Sur site",
      "description": "Nous recherchons un Développeur Full Stack pour rejoindre notre équipe. Maîtrise requise : JavaScript, SQL, AWS, Power BI, Python.",
      "competences_brut": "JavaScript, SQL, AWS, Power BI, Python"
    },
    {
      "id_offre": "MEX-13296",
      "source": "MenaJobs",
      "titre_poste": "Développeur Frontend 1 à 3 ans",
      "entreprise": "TechCorp 5",
      "ville": "Rabat",
      "date_publication": "2023-08-27",
      "type_contrat": "CDI",
      "salaire_brut": "À débattre",
      "experience_requise": "1 à 3 ans",
      "teletravail": "Hybride",
      "description": "Nous recherchons un Développeur Frontend pour rejoindre notre équipe. Maîtrise requise : PostgreSQL, Power BI, Python, Docker, Spark.",
      "competences_brut": "PostgreSQL, Power BI, Python, Docker, Spark"
    },
    {
      "id_offre": "MEX-13334",
      "source": "MenaJobs",
      "titre_poste": "Data Scientist 3 à 5 ans",
      "entreprise": "TechCorp 16",
      "ville": "Marrakech",
      "date_publication": "2023-08-25",
      "type_contrat": "CDI",
      "salaire_brut": "À débattre",
      "experience_requise": "3 à 5 ans",
      "teletravail": "Télétravail total",
      "description": "Nous recherchons un Data Scientist pour rejoindre notre équipe. Maîtrise requise : JavaScript, Java, Docker, PostgreSQL.",
      "competences_brut": "JavaScript, Java, Docker, PostgreSQL"
    },
    {
      "id_offre": "MEX-13347",
      "source": "MenaJobs",
      "titre_poste": "Développeur Frontend Senior (5+ ans)",
      "entreprise": "TechCorp 38",
      "ville": "Casablanca",
      "date_publication": "2023-08-24",
      "type_contrat": "CDD",
      "salaire_brut": "18000 à 27000 DH",
      "experience_requise": "Senior (5+ ans)",
      "teletravail": "Hybride",
      "description": "Nous recherchons un Développeur Frontend pour rejoindre notre équipe. Maîtrise requise : PostgreSQL, Docker.",
      "competences_brut": "PostgreSQL, Docker"
    },
    {
      "id_offre": "MEX-13371",
      "source": "MenaJobs",
      "titre_poste": "Data Engineer 3 à 5 ans",
      "entreprise": "TechCorp 36",
      "ville": "Casablanca",
      "date_publication": "2023-08-18",
      "type_contrat": "CDI",
      "salaire_brut": "21K - 30K MAD",
      "experience_requise": "3 à 5 ans",
      "teletravail": "Sur site",
      "description": "Nous recherchons un Data Engineer pour rejoindre notre équipe. Maîtrise requise : PostgreSQL, Power BI, Airflow, Java.",
      "competences_brut": "PostgreSQL, Power BI, Airflow, Java"
    },
    {
      "id_offre": "MEX-13428",
      "source": "MenaJobs",
      "titre_poste": "Data Analyst 1 à 3 ans",
      "entreprise": "TechCorp 10",
      "ville": "Tanger",
      "date_publication": "2023-08-03",
      "type_contrat": "CDI",
      "salaire_brut": "10K - 16K MAD",
      "experience_requise": "1 à 3 ans",
      "teletravail": "Télétravail total",
      "description": "Nous recherchons un Data Analyst pour rejoindre notre équipe. Maîtrise requise : Python, React, Kafka, JavaScript.",
      "competences_brut": "Python, React, Kafka, JavaScript"
    },
    {
      "id_offre": "MEX-13503",
      "source": "MenaJobs",
      "titre_poste": "DevOps Senior (5+ ans)",
      "entreprise": "TechCorp 3",
      "ville": "Marrakech",
      "date_publication": "2023-08-20",
      "type_contrat": "Freelance",
      "salaire_brut": "25000 à 36000 DH",
      "experience_requise": "Senior (5+ ans)",
      "teletravail": "Hybride",
      "description": "Nous recherchons un DevOps pour rejoindre notre équipe. Maîtrise requise : Spark, Kafka, Airflow, Power BI.",
      "competences_brut": "Spark, Kafka, Airflow, Power BI"
    },
    {
      "id_offre": "MEX-13526",
      "source": "MenaJobs",
      "titre_poste": "Support IT 1 à 3 ans",
      "entreprise": "TechCorp 40",
      "ville": "Tanger",
      "date_publication": "2023-08-10",
      "type_contrat": "CDI",
      "salaire_brut": "5000 à 8000 DH",
      "experience_requise": "1 à 3 ans",
      "teletravail": "Télétravail total",
      "description": "Nous recherchons un Support IT pour rejoindre notre équipe. Maîtrise requise : AWS, Kafka, Java, SQL.",
      "competences_brut": "AWS, Kafka, Java, SQL"
    },
    {
      "id_offre": "MEX-13539",
      "source": "MenaJobs",
      "titre_poste": "Développeur Frontend 1 à 3 ans",
      "entreprise": "TechCorp 10",
      "ville": "Fès",
      "date_publication": "2023-08-22",
      "type_contrat": "CDI",
      "salaire_brut": "10000 à 15000 DH",
      "experience_requise": "1 à 3 ans",
      "teletravail": "Hybride",
      "description": "Nous recherchons un Développeur Frontend pour rejoindre notre équipe. Maîtrise requise : React, Airflow.",
      "competences_brut": "React, Airflow"
    },
    {
      "id_offre": "MEX-13559",
      "source": "MenaJobs",
      "titre_poste": "Data Scientist 3 à 5 ans",
      "entreprise": "TechCorp 28",
      "ville": "Casablanca",
      "date_publication": "2023-08-02",
      "type_contrat": "Freelance",
      "salaire_brut": "Selon profil",
      "experience_requise": "3 à 5 ans",
      "teletravail": "Hybride",
      "description": "Nous recherchons un Data Scientist pour rejoindre notre équipe. Maîtrise requise : Java, Python, Airflow.",
      "competences_brut": "Java, Python, Airflow"
    },
    {
      "id_offre": "MEX-13571",
      "source": "MenaJobs",
      "titre_poste": "Support IT 1 à 3 ans",
      "entreprise": "TechCorp 8",
      "ville": "Marrakech",
      "date_publication": "2023-08-31",
      "type_contrat": "CDI",
      "salaire_brut": "5000 à 8000 DH",
      "experience_requise": "1 à 3 ans",
      "teletravail": "Télétravail total",
      "description": "Nous recherchons un Support IT pour rejoindre notre équipe. Maîtrise requise : React, Spark.",
      "competences_brut": "React, Spark"
    },
    {
      "id_offre": "MEX-13574",
      "source": "MenaJobs",
      "titre_poste": "DevOps Senior (5+ ans)",
      "entreprise": "TechCorp 29",
      "ville": "Tanger",
      "date_publication": "2023-08-10",
      "type_contrat": "CDD",
      "salaire_brut": "25000 à 36000 DH",
      "experience_requise": "Senior (5+ ans)",
      "teletravail": "Télétravail total",
      "description": "Nous recherchons un DevOps pour rejoindre notre équipe. Maîtrise requise : Airflow, JavaScript.",
      "competences_brut": "Airflow, JavaScript"
    },
    {
      "id_offre": "MEX-13690",
      "source": "MenaJobs",
      "titre_poste": "Data Scientist Senior (5+ ans)",
      "entreprise": "TechCorp 41",
      "ville": "Rabat",
      "date_publication": "2023-08-12",
      "type_contrat": "CDI",
      "salaire_brut": "28K - 43K MAD",
      "experience_requise": "Senior (5+ ans)",
      "teletravail": "Hybride",
      "description": "Nous recherchons un Data Scientist pour rejoindre notre équipe. Maîtrise requise : SQL, PostgreSQL, Spark, AWS, React.",
      "competences_brut": "SQL, PostgreSQL, Spark, AWS, React"
    },
    {
      "id_offre": "MEX-13760",
      "source": "MenaJobs",
      "titre_poste": "Architecte IT Expert (8+ ans)",
      "entreprise": "TechCorp 1",
      "ville": "Tanger",
      "date_publication": "2023-08-26",
      "type_contrat": "CDI",
      "salaire_brut": "55000 à 77000 DH",
      "experience_requise": "Expert (8+ ans)",
      "teletravail": "Sur site",
      "description": "Nous recherchons un Architecte IT pour rejoindre notre équipe. Maîtrise requise : Docker, JavaScript, PostgreSQL.",
      "competences_brut": "Docker, JavaScript, PostgreSQL"
    },
    {
      "id_offre": "MEX-13771",
      "source": "MenaJobs",
      "titre_poste": "Data Scientist 1 à 3 ans",
      "entreprise": "TechCorp 27",
      "ville": "Casablanca",
      "date_publication": "2023-08-11",
      "type_contrat": "CDI",
      "salaire_brut": "16000 à 24000 DH",
      "experience_requise": "1 à 3 ans",
      "teletravail": "Télétravail total",
      "description": "Nous recherchons un Data Scientist pour rejoindre notre équipe. Maîtrise requise : AWS, Spark, PostgreSQL.",
      "competences_brut": "AWS, Spark, PostgreSQL"
    },
    {
      "id_offre": "MEX-13932",
      "source": "MenaJobs",
      "titre_poste": "Admin Systèmes & Réseaux 1 à 3 ans",
      "entreprise": "TechCorp 49",
      "ville": "Casablanca",
      "date_publication": "2023-08-12",
      "type_contrat": "CDI",
      "salaire_brut": "8K - 12K MAD",
      "experience_requise": "1 à 3 ans",
      "teletravail": "Hybride",
      "description": "Nous recherchons un Admin Systèmes & Réseaux pour rejoindre notre équipe. Maîtrise requise : Java, Python.",
      "competences_brut": "Java, Python"
    },
    {
      "id_offre": "MEX-13958",
      "source": "MenaJobs",
      "titre_poste": "Data Engineer Senior (5+ ans)",
      "entreprise": "TechCorp 43",
      "ville": "Casablanca",
      "date_publication": "2023-08-23",
      "type_contrat": "CDI",
      "salaire_brut": "27K - 39K MAD",
      "experience_requise": "Senior (5+ ans)",
      "teletravail": "Hybride",
      "description": "Nous recherchons un Data Engineer pour rejoindre notre équipe. Maîtrise requise : React, PostgreSQL, JavaScript, Airflow, Kafka.",
      "competences_brut": "React, PostgreSQL, JavaScript, Airflow, Kafka"
    },
    {
      "id_offre": "MEX-13981",
      "source": "MenaJobs",
      "titre_poste": "Data Engineer 1 à 3 ans",
      "entreprise": "TechCorp 23",
      "ville": "Tanger",
      "date_publication": "2023-08-15",
      "type_contrat": "CDI",
      "salaire_brut": "15K - 22K MAD",
      "experience_requise": "1 à 3 ans",
      "teletravail": "Télétravail total",
      "description": "Nous recherchons un Data Engineer pour rejoindre notre équipe. Maîtrise requise : AWS, JavaScript, Power BI, Spark, PostgreSQL.",
      "competences_brut": "AWS, JavaScript, Power BI, Spark, PostgreSQL"
    },
    {
      "id_offre": "MEX-13995",
      "source": "MenaJobs",
      "titre_poste": "Admin Systèmes & Réseaux 1 à 3 ans",
      "entreprise": "TechCorp 50",
      "ville": "Rabat",
      "date_publication": "2023-08-20",
      "type_contrat": "CDI",
      "salaire_brut": "8K - 12K MAD",
      "experience_requise": "1 à 3 ans",
      "teletravail": "Hybride",
      "description": "Nous recherchons un Admin Systèmes & Réseaux pour rejoindre notre équipe. Maîtrise requise : Power BI, Docker, Python, JavaScript, React.",
      "competences_brut": "Power BI, Docker, Python, JavaScript, React"
    },
    {
      "id_offre": "MEX-13997",
      "source": "MenaJobs",
      "titre_poste": "Architecte IT Débutant",
      "entreprise": "TechCorp 45",
      "ville": "Tanger",
      "date_publication": "2023-08-13",
      "type_contrat": "CDI",
      "salaire_brut": "20000 à 28000 DH",
      "experience_requise": "Débutant",
      "teletravail": "Télétravail total",
      "description": "Nous recherchons un Architecte IT pour rejoindre notre équipe. Maîtrise requise : PostgreSQL, Java, Kafka.",
      "competences_brut": "PostgreSQL, Java, Kafka"
    },
    {
      "id_offre": "MEX-14030",
      "source": "MenaJobs",
      "titre_poste": "Data Scientist Débutant",
      "entreprise": "TechCorp 2",
      "ville": "Fès",
      "date_publication": "2023-08-15",
      "type_contrat": "CDI",
      "salaire_brut": "12K - 19K MAD",
      "experience_requise": "Débutant",
      "teletravail": "Sur site",
      "description": "Nous recherchons un Data Scientist pour rejoindre notre équipe. Maîtrise requise : Power BI, React, SQL, JavaScript.",
      "competences_brut": "Power BI, React, SQL, JavaScript"
    },
    {
      "id_offre": "MEX-14156",
      "source": "MenaJobs",
      "titre_poste": "Architecte IT Senior (5+ ans)",
      "entreprise": "TechCorp 34",
      "ville": "Rabat",
      "date_publication": "2023-08-20",
      "type_contrat": "CDI",
      "salaire_brut": "45K - 63K MAD",
      "experience_requise": "Senior (5+ ans)",
      "teletravail": "Sur site",
      "description": "Nous recherchons un Architecte IT pour rejoindre notre équipe. Maîtrise requise : PostgreSQL, Docker, AWS, JavaScript.",
      "competences_brut": "PostgreSQL, Docker, AWS, JavaScript"
    },
    {
      "id_offre": "MEX-14166",
      "source": "MenaJobs",
      "titre_poste": "Data Analyst 3 à 5 ans",
      "entreprise": "TechCorp 16",
      "ville": "Casablanca",
      "date_publication": "2023-08-03",
      "type_contrat": "Freelance",
      "salaire_brut": "14000 à 22000 DH",
      "experience_requise": "3 à 5 ans",
      "teletravail": "Hybride",
      "description": "Nous recherchons un Data Analyst pour rejoindre notre équipe. Maîtrise requise : Power BI, Spring.",
      "competences_brut": "Power BI, Spring"
    },
    {
      "id_offre": "MEX-14256",
      "source": "MenaJobs",
      "titre_poste": "Admin Systèmes & Réseaux 3 à 5 ans",
      "entreprise": "TechCorp 23",
      "ville": "Casablanca",
      "date_publication": "2023-08-07",
      "type_contrat": "CDD",
      "salaire_brut": "11K - 16K MAD",
      "experience_requise": "3 à 5 ans",
      "teletravail": "Sur site",
      "description": "Nous recherchons un Admin Systèmes & Réseaux pour rejoindre notre équipe. Maîtrise requise : Kafka, AWS, Docker, Airflow, JavaScript.",
      "competences_brut": "Kafka, AWS, Docker, Airflow, JavaScript"
    },
    {
      "id_offre": "MEX-14374",
      "source": "MenaJobs",
      "titre_poste": "Développeur Full Stack 3 à 5 ans",
      "entreprise": "TechCorp 7",
      "ville": "Casablanca",
      "date_publication": "2023-08-02",
      "type_contrat": "CDI",
      "salaire_brut": "16K - 25K MAD",
      "experience_requise": "3 à 5 ans",
      "teletravail": "Télétravail total",
      "description": "Nous recherchons un Développeur Full Stack pour rejoindre notre équipe. Maîtrise requise : PostgreSQL, SQL, JavaScript, Spark, Docker.",
      "competences_brut": "PostgreSQL, SQL, JavaScript, Spark, Docker"
    },
    {
      "id_offre": "MEX-14391",
      "source": "MenaJobs",
      "titre_poste": "Data Analyst 1 à 3 ans",
      "entreprise": "TechCorp 34",
      "ville": "Casablanca",
      "date_publication": "2023-08-08",
      "type_contrat": "CDI",
      "salaire_brut": "10K - 16K MAD",
      "experience_requise": "1 à 3 ans",
      "teletravail": "Télétravail total",
      "description": "Nous recherchons un Data Analyst pour rejoindre notre équipe. Maîtrise requise : JavaScript, Python.",
      "competences_brut": "JavaScript, Python"
    },
    {
      "id_offre": "MEX-14477",
      "source": "MenaJobs",
      "titre_poste": "Data Analyst 1 à 3 ans",
      "entreprise": "TechCorp 16",
      "ville": "Tanger",
      "date_publication": "2023-08-09",
      "type_contrat": "CDI",
      "salaire_brut": "10K - 16K MAD",
      "experience_requise": "1 à 3 ans",
      "teletravail": "Hybride",
      "description": "Nous recherchons un Data Analyst pour rejoindre notre équipe. Maîtrise requise : Docker, Spring.",
      "competences_brut": "Docker, Spring"
    },
    {
      "id_offre": "MEX-14503",
      "source": "MenaJobs",
      "titre_poste": "Support IT 1 à 3 ans",
      "entreprise": "TechCorp 18",
      "ville": "Casablanca",
      "date_publication": "2023-08-12",
      "type_contrat": "CDI",
      "salaire_brut": "5000 à 8000 DH",
      "experience_requise": "1 à 3 ans",
      "teletravail": "Hybride",
      "description": "Nous recherchons un Support IT pour rejoindre notre équipe. Maîtrise requise : PostgreSQL, Spark.",
      "competences_brut": "PostgreSQL, Spark"
    },
    {
      "id_offre": "MEX-14553",
      "source": "MenaJobs",
      "titre_poste": "Data Analyst 1 à 3 ans",
      "entreprise": "TechCorp 40",
      "ville": "Marrakech",
      "date_publication": "2023-08-28",
      "type_contrat": "CDI",
      "salaire_brut": "10000 à 16000 DH",
      "experience_requise": "1 à 3 ans",
      "teletravail": "Sur site",
      "description": "Nous recherchons un Data Analyst pour rejoindre notre équipe. Maîtrise requise : React, Spring.",
      "competences_brut": "React, Spring"
    },
    {
      "id_offre": "MEX-14574",
      "source": "MenaJobs",
      "titre_poste": "DevOps Senior (5+ ans)",
      "entreprise": "TechCorp 13",
      "ville": "Rabat",
      "date_publication": "2023-08-23",
      "type_contrat": "CDI",
      "salaire_brut": "25000 à 36000 DH",
      "experience_requise": "Senior (5+ ans)",
      "teletravail": "Hybride",
      "description": "Nous recherchons un DevOps pour rejoindre notre équipe. Maîtrise requise : Kafka, Python, Spring, Airflow.",
      "competences_brut": "Kafka, Python, Spring, Airflow"
    },
    {
      "id_offre": "MEX-14660",
      "source": "MenaJobs",
      "titre_poste": "Data Analyst 3 à 5 ans",
      "entreprise": "TechCorp 39",
      "ville": "Marrakech",
      "date_publication": "2023-08-19",
      "type_contrat": "CDI",
      "salaire_brut": "14K - 22K MAD",
      "experience_requise": "3 à 5 ans",
      "teletravail": "Sur site",
      "description": "Nous recherchons un Data Analyst pour rejoindre notre équipe. Maîtrise requise : Airflow, Power BI, PostgreSQL, Java.",
      "competences_brut": "Airflow, Power BI, PostgreSQL, Java"
    },
    {
      "id_offre": "MEX-14716",
      "source": "MenaJobs",
      "titre_poste": "Architecte IT 1 à 3 ans",
      "entreprise": "TechCorp 2",
      "ville": "Tanger",
      "date_publication": "2023-08-08",
      "type_contrat": "CDI",
      "salaire_brut": "25000 à 35000 DH",
      "experience_requise": "1 à 3 ans",
      "teletravail": "Télétravail total",
      "description": "Nous recherchons un Architecte IT pour rejoindre notre équipe. Maîtrise requise : SQL, Spring, Spark.",
      "competences_brut": "SQL, Spring, Spark"
    },
    {
      "id_offre": "MEX-14724",
      "source": "MenaJobs",
      "titre_poste": "Data Engineer 3 à 5 ans",
      "entreprise": "TechCorp 35",
      "ville": "Casablanca",
      "date_publication": "2023-08-24",
      "type_contrat": "CDD",
      "salaire_brut": "21000 à 30000 DH",
      "experience_requise": "3 à 5 ans",
      "teletravail": "Télétravail total",
      "description": "Nous recherchons un Data Engineer pour rejoindre notre équipe. Maîtrise requise : Power BI, SQL, Airflow, Spark.",
      "competences_brut": "Power BI, SQL, Airflow, Spark"
    },
    {
      "id_offre": "MEX-14874",
      "source": "MenaJobs",
      "titre_poste": "Data Analyst 3 à 5 ans",
      "entreprise": "TechCorp 30",
      "ville": "Rabat",
      "date_publication": "2023-08-10",
      "type_contrat": "Freelance",
      "salaire_brut": "14000 à 22000 DH",
      "experience_requise": "3 à 5 ans",
      "teletravail": "Sur site",
      "description": "Nous recherchons un Data Analyst pour rejoindre notre équipe. Maîtrise requise : Airflow, Docker, React, Kafka.",
      "competences_brut": "Airflow, Docker, React, Kafka"
    },
    {
      "id_offre": "MEX-14964",
      "source": "MenaJobs",
      "titre_poste": "Développeur Full Stack Débutant",
      "entreprise": "TechCorp 42",
      "ville": "Casablanca",
      "date_publication": "2023-08-10",
      "type_contrat": "CDI",
      "salaire_brut": "9K - 14K MAD",
      "experience_requise": "Débutant",
      "teletravail": "Sur site",
      "description": "Nous recherchons un Développeur Full Stack pour rejoindre notre équipe. Maîtrise requise : Kafka, JavaScript, SQL, Java, Power BI.",
      "competences_brut": "Kafka, JavaScript, SQL, Java, Power BI"
    }
  ]
}